pretty_format_json/__init__.py
pretty_format_json/csv_json.py
pretty_format_json/format.py
pretty_format_json/yaml_json.py
pretty_format_json-0.2.22.dist-info/METADATA
pretty_format_json-0.2.22.dist-info/WHEEL
pretty_format_json-0.2.22.dist-info/entry_points.txt
pretty_format_json-0.2.22.dist-info/top_level.txt
pretty_format_json-0.2.22.dist-info/RECORD
