Metadata-Version: 2.1
Name: pretty-format-json
Version: 0.2.22
Summary: Pretty print json contains python style coments, string literal.
Home-page: https://github.com/weaming/pretty-format-json
Author: weaming
Author-email: garden.yuen@gmail.com
License: UNKNOWN
Project-URL: Source, https://github.com/weaming/pretty-format-json
Project-URL: Bug Reports, https://github.com/weaming/pretty-format-json
Keywords: json format
Platform: UNKNOWN
Requires-Dist: oyaml
Requires-Dist: data-process (>=0.3.*)
